random_32_key_base64/__init__.py
random_32_key_base64/py.typed
random_32_key_base64-0.1.0.dist-info/METADATA
random_32_key_base64-0.1.0.dist-info/WHEEL
random_32_key_base64-0.1.0.dist-info/entry_points.txt
random_32_key_base64-0.1.0.dist-info/top_level.txt
random_32_key_base64-0.1.0.dist-info/RECORD
