Metadata-Version: 2.4
Name: random-32-key-base64
Version: 0.1.0
Summary: Generate a 32-byte random key using random.org and encode it in base64
Author-email: David Walker <dbwalker0min@gmail.com>
Requires-Python: >=3.12
